cyber_radar/__init__.py
cyber_radar/automation_managers.py
cyber_radar/client_configuration_manager.py
cyber_radar/client_uplink_connection.py
cyber_radar/constants.py
cyber_radar/distributed.py
cyber_radar/system_command.py
cyber_radar/uplink_server_connection.py
cyber_radar/commanders/__init__.py
cyber_radar/commanders/map_network.py
cyber_radar/config/client_config.toml
cyber_radar/config/server_config.toml
cyber_radar/config/uplink_config.toml
cyber_radar/helpers/__init__.py
cyber_radar/helpers/target_formatter.py
cyber_radar/helpers/target_prioritizer.py
cyber_radar/parsers/__init__.py
cyber_radar/parsers/parser_nmap.py
cyber_radar/playbooks/__init__.py
cyber_radar/playbooks/enum_msrpc.py
cyber_radar/playbooks/grab_ftp_file_list.py
cyber_radar/playbooks/scan_anon_ftp.py
cyber_radar/rules/parsing_rules.yara
cyber_radar/rules/playbook_rules.yara
cyber_radar-0.3.5.data/scripts/radar-ctl.py
cyber_radar-0.3.5.data/scripts/radar-server.py
cyber_radar-0.3.5.data/scripts/radar-uplink.py
cyber_radar-0.3.5.data/scripts/radar.py
cyber_radar-0.3.5.dist-info/LICENSE
cyber_radar-0.3.5.dist-info/METADATA
cyber_radar-0.3.5.dist-info/WHEEL
cyber_radar-0.3.5.dist-info/top_level.txt
cyber_radar-0.3.5.dist-info/RECORD
