Metadata-Version: 2.1
Name: cyber-radar
Version: 0.3.5
Summary: A framework to support a Red-team Analysis, Documentation, and Automation Revolution!
Home-page: https://github.com/sevaarcen/RADAR
Author: Cole Daubenspeck
Author-email: coleipod@gmail.com
License: GPLv3
Platform: UNKNOWN
Classifier: Programming Language :: Python :: 3
Classifier: Operating System :: OS Independent
Classifier: Development Status :: 4 - Beta
Requires-Python: >=3.6
Requires-Dist: toml (~=0.10)
Requires-Dist: yara-python (~=4.0)
Requires-Dist: netaddr (~=0.8)
Requires-Dist: certifi (~=2019.9)
Requires-Dist: chardet (~=3.0)
Requires-Dist: Click (~=7.0)
Requires-Dist: Flask (~=1.1)
Requires-Dist: Flask-Script (~=2.0)
Requires-Dist: idna (~=2.8)
Requires-Dist: itsdangerous (~=1.1)
Requires-Dist: Jinja2 (~=2.10)
Requires-Dist: MarkupSafe (~=1.1)
Requires-Dist: pymongo (~=3.9)
Requires-Dist: python-dateutil (~=2.8)
Requires-Dist: requests (~=2.22)
Requires-Dist: six (~=1.12)
Requires-Dist: urllib3 (~=1.25)
Requires-Dist: Werkzeug (~=0.16)
Requires-Dist: tqdm (~=4.55)
Requires-Dist: numpy (==1.19.3)
Requires-Dist: pandas (~=1.2.0)
